django_taggit_tronc-0.21.2.dist-info/DESCRIPTION.rst
django_taggit_tronc-0.21.2.dist-info/LICENSE.txt
django_taggit_tronc-0.21.2.dist-info/METADATA
django_taggit_tronc-0.21.2.dist-info/RECORD
django_taggit_tronc-0.21.2.dist-info/WHEEL
django_taggit_tronc-0.21.2.dist-info/metadata.json
django_taggit_tronc-0.21.2.dist-info/top_level.txt
taggit/__init__.py
taggit/admin.py
taggit/apps.py
taggit/forms.py
taggit/managers.py
taggit/models.py
taggit/utils.py
taggit/views.py
taggit/locale/cs/LC_MESSAGES/django.mo
taggit/locale/cs/LC_MESSAGES/django.po
taggit/locale/de/LC_MESSAGES/django.mo
taggit/locale/de/LC_MESSAGES/django.po
taggit/locale/el/LC_MESSAGES/django.mo
taggit/locale/el/LC_MESSAGES/django.po
taggit/locale/en/LC_MESSAGES/django.po
taggit/locale/eo/LC_MESSAGES/django.mo
taggit/locale/eo/LC_MESSAGES/django.po
taggit/locale/es/LC_MESSAGES/django.mo
taggit/locale/es/LC_MESSAGES/django.po
taggit/locale/he/LC_MESSAGES/django.mo
taggit/locale/he/LC_MESSAGES/django.po
taggit/locale/it/LC_MESSAGES/django.mo
taggit/locale/it/LC_MESSAGES/django.po
taggit/locale/ja/LC_MESSAGES/django.mo
taggit/locale/ja/LC_MESSAGES/django.po
taggit/locale/nb/LC_MESSAGES/django.mo
taggit/locale/nb/LC_MESSAGES/django.po
taggit/locale/nl/LC_MESSAGES/django.mo
taggit/locale/nl/LC_MESSAGES/django.po
taggit/locale/pt_BR/LC_MESSAGES/django.mo
taggit/locale/pt_BR/LC_MESSAGES/django.po
taggit/locale/ru/LC_MESSAGES/django.mo
taggit/locale/ru/LC_MESSAGES/django.po
taggit/locale/tr/LC_MESSAGES/django.mo
taggit/locale/tr/LC_MESSAGES/django.po
taggit/locale/zh_Hans/LC_MESSAGES/django.mo
taggit/locale/zh_Hans/LC_MESSAGES/django.po
taggit/migrations/0001_initial.py
taggit/migrations/0002_auto_20150616_2121.py
taggit/migrations/__init__.py
