Metadata-Version: 2.0
Name: django-taggit-tronc
Version: 0.21.2
Summary: django-taggit is a reusable Django application for simple tagging.
Home-page: https://github.com/troncx/django-taggit
Author: Maintained by Charley Bodkin / Tronc. Originally by Alex Gaynor
Author-email: charley.bodkin@latimes.com
License: BSD
Platform: UNKNOWN
Classifier: Development Status :: 5 - Production/Stable
Classifier: Environment :: Web Environment
Classifier: Framework :: Django
Classifier: Framework :: Django :: 1.7
Classifier: Framework :: Django :: 1.8
Classifier: Framework :: Django :: 1.9
Classifier: Framework :: Django :: 1.10
Classifier: Intended Audience :: Developers
Classifier: License :: OSI Approved :: BSD License
Classifier: Operating System :: OS Independent
Classifier: Programming Language :: Python
Classifier: Programming Language :: Python :: 2.7
Classifier: Programming Language :: Python :: 3.3
Classifier: Programming Language :: Python :: 3.4
Classifier: Programming Language :: Python :: 3.5
